ztfparsnip/BTS_plus_TDE/ZTF18aamvfeb_bl.csv
ztfparsnip/BTS_plus_TDE/ZTF18aavvnzu_bl.csv
ztfparsnip/BTS_plus_TDE/ZTF18aawgrxz_bl.csv
ztfparsnip/BTS_plus_TDE/ZTF19aapreis_bl.csv
ztfparsnip/BTS_plus_TDE/ZTF20actpavu_bl.csv
ztfparsnip/BTS_plus_TDE/ZTF20acueziy_bl.csv
ztfparsnip/BTS_plus_TDE/ZTF20acuobve_bl.csv
ztfparsnip/BTS_plus_TDE/ZTF20acvkjrm_bl.csv
ztfparsnip/BTS_plus_TDE/ZTF20acvmzfv_bl.csv
ztfparsnip/BTS_plus_TDE/ZTF20acwjhpo_bl.csv
ztfparsnip/BTS_plus_TDE/headers.json
ztfparsnip/__init__.py
ztfparsnip/create.py
ztfparsnip/io.py
ztfparsnip/noisify.py
ztfparsnip/plot.py
ztfparsnip/train.py
ztfparsnip-0.3.0.dist-info/LICENSE
ztfparsnip-0.3.0.dist-info/METADATA
ztfparsnip-0.3.0.dist-info/WHEEL
ztfparsnip-0.3.0.dist-info/entry_points.txt
ztfparsnip-0.3.0.dist-info/RECORD
