Metadata-Version: 2.1
Name: ztfparsnip
Version: 0.3.0
Summary: Generate noisified lightcurves based on the BTS sample and retrain Parsnip with these.
Author: Simeon Reusch
Author-email: simeon.reusch@desy.de
Requires-Python: >=3.10,<3.12
Classifier: Programming Language :: Python :: 3
Classifier: Programming Language :: Python :: 3.10
Classifier: Programming Language :: Python :: 3.11
Requires-Dist: astro-parsnip (>=1.3.1,<2.0.0)
Requires-Dist: h5py (>=3.7.0,<4.0.0)
Requires-Dist: numpy (>=1.24.0,<2.0.0)
Requires-Dist: pandas (>=1.5.2,<2.0.0)
Requires-Dist: pandas-stubs (>=1.5.2.230105,<2.0.0.0)
Requires-Dist: seaborn (>=0.12.2,<0.13.0)
Requires-Dist: tqdm (>=4.64.1,<5.0.0)
Requires-Dist: tqdm-stubs (>=0.2.1,<0.3.0)
Requires-Dist: types-pyyaml (>=6.0.12.8,<7.0.0.0)
